{"Diffusion (disambiguation)": "/wiki/Diffusion_(disambiguation)", "Enlarge": "/wiki/File:Diffusion.svg", "Dissolution (chemistry)": "/wiki/Dissolution_(chemistry)", "Flux": "/wiki/Flux", "Solute": "/wiki/Solute", "Force": "/wiki/Force", "Entropic force": "/wiki/Entropic_force", "Concentration": "/wiki/Concentration", "Gibbs free energy": "/wiki/Gibbs_free_energy", "Chemical potential": "/wiki/Chemical_potential", "Quantum Physics": "/wiki/Quantum_Physics", "Wave packets": "/wiki/Wave_packets", "Spinodal decomposition": "/wiki/Spinodal_decomposition", "Statistics": "/wiki/Statistics", "Probability theory": "/wiki/Probability_theory", "Information theory": "/wiki/Information_theory", "Neural networks": "/wiki/Neural_networks", "Finance": "/wiki/Finance", "Marketing": "/wiki/Marketing", "Physics": "/wiki/Physics", "Molecular diffusion": "/wiki/Molecular_diffusion", "Chemistry": "/wiki/Chemistry", "Biology": "/wiki/Biology", "Sociology": "/wiki/Sociology", "Economics": "/wiki/Economics", "Data science": "/wiki/Data_science", "Statistical physics": "/wiki/Statistical_physics", "Gradient": "/wiki/Gradient", "Pressure": "/wiki/Pressure", "Temperature": "/wiki/Temperature", "Distance": "/wiki/Distance", "Pressure gradient": "/wiki/Pressure_gradient", "Temperature gradient": "/wiki/Temperature_gradient", "Latin": "/wiki/Latin", "Random walk": "/wiki/Random_walk", "Advection": "/wiki/Advection", "Convection": "/wiki/Convection", "Transport phenomena": "/wiki/Transport_phenomena", "Fick's laws of diffusion": "/wiki/Fick%27s_laws_of_diffusion", "Anomalous diffusion": "/wiki/Anomalous_diffusion", "Brownian motion": "/wiki/Brownian_motion", "Impulse response": "/wiki/Impulse_response", "Mean squared displacement": "/wiki/Mean_squared_displacement", "Dimension": "/wiki/Dimension", "Edit section: Diffusion vs. bulk flow": "/w/index.php?title=Diffusion&action=edit&section=1", "Mass flow": "/wiki/Mass_flow", "Lungs": "/wiki/Lungs", "Thoracic cavity": "/wiki/Thoracic_cavity", "Pulmonary alveolus": "/wiki/Pulmonary_alveolus", "Air": "/wiki/Air", "Capillaries": "/wiki/Capillaries", "Carbon dioxide": "/wiki/Carbon_dioxide", "Blood": "/wiki/Blood", "Heart": "/wiki/Heart", "Blood vessel": "/wiki/Blood_vessel", "Edit section: Diffusion in the context of different disciplines": "/w/index.php?title=Diffusion&action=edit&section=2", "Thermal oxidation": "/wiki/Thermal_oxidation", "wikt:phenomenon": "https://en.wiktionary.org/wiki/phenomenon", "Thermodynamics": "/wiki/Thermodynamics", "Non-equilibrium thermodynamics": "/wiki/Non-equilibrium_thermodynamics", "Robert Brown (botanist, born 1773)": "/wiki/Robert_Brown_(botanist,_born_1773)", "Albert Einstein": "/wiki/Albert_Einstein", "Statistical ensemble (mathematical physics)": "/wiki/Statistical_ensemble_(mathematical_physics)", "Materials science": "/wiki/Materials_science", "Knudsen diffusion": "/wiki/Knudsen_diffusion", "Mass diffusivity": "/wiki/Mass_diffusivity", "Biologist": "/wiki/Biologist", "Probability": "/wiki/Probability", "Edit section: History of diffusion in physics": "/w/index.php?title=Diffusion&action=edit&section=3", "Pliny the Elder": "/wiki/Pliny_the_Elder", "Cementation process": "/wiki/Cementation_process", "Iron": "/wiki/Iron", "Stained glass": "/wiki/Stained_glass", "Earthenware": "/wiki/Earthenware", "Chinese ceramics": "/wiki/Chinese_ceramics", "Thomas Graham (chemist)": "/wiki/Thomas_Graham_(chemist)", "James Clerk Maxwell": "/wiki/James_Clerk_Maxwell", "Adolf Fick": "/wiki/Adolf_Fick", "Thermal conduction": "/wiki/Thermal_conduction", "Ohm's law": "/wiki/Ohm%27s_law", "Robert Boyle": "/wiki/Robert_Boyle", "William Chandler Roberts-Austen": "/wiki/William_Chandler_Roberts-Austen", "Rudolf Clausius": "/wiki/Rudolf_Clausius", "Mean free path": "/wiki/Mean_free_path", "Marian Smoluchowski": "/wiki/Marian_Smoluchowski", "Jean-Baptiste Perrin": "/wiki/Jean-Baptiste_Perrin", "Ludwig Boltzmann": "/wiki/Ludwig_Boltzmann", "Boltzmann equation": "/wiki/Boltzmann_equation", "George de Hevesy": "/wiki/George_de_Hevesy", "Self-diffusion": "/wiki/Self-diffusion", "Radioisotope": "/wiki/Radioisotope", "Yakov Frenkel": "/wiki/Yakov_Frenkel", "Interstitial defect": "/wiki/Interstitial_defect", "Carl Wagner": "/wiki/Carl_Wagner", "Walter H. Schottky": "/wiki/Walter_H._Schottky", "Henry Eyring (chemist)": "/wiki/Henry_Eyring_(chemist)", "Transition state theory": "/wiki/Transition_state_theory", "Chemical kinetics": "/wiki/Chemical_kinetics", "Edit section: Basic models of diffusion": "/w/index.php?title=Diffusion&action=edit&section=4", "Edit section: Diffusion flux": "/w/index.php?title=Diffusion&action=edit&section=5", "Area": "/wiki/Area", "Physical quantity": "/wiki/Physical_quantity", "Inner product": "/wiki/Inner_product", "Little-o notation": "/wiki/Little-o_notation", "Vector area": "/wiki/Vector_area", "Dimensional analysis": "/wiki/Dimensional_analysis", "Extensive quantity": "/wiki/Extensive_quantity", "Edit section: Fick's law and equations": "/w/index.php?title=Diffusion&action=edit&section=6", "Laplace operator": "/wiki/Laplace_operator", "Edit section: Onsager's equations for multicomponent diffusion and thermodiffusion": "/w/index.php?title=Diffusion&action=edit&section=7", "Lars Onsager": "/wiki/Lars_Onsager", "Conjugate variables (thermodynamics)": "/wiki/Conjugate_variables_(thermodynamics)", "Entropy": "/wiki/Entropy", "Onsager reciprocal relations": "/wiki/Onsager_reciprocal_relations", "Positive-definite matrix": "/wiki/Positive-definite_matrix", "Second law of thermodynamics": "/wiki/Second_law_of_thermodynamics", "Thermal conductivity": "/wiki/Thermal_conductivity", "Isothermal process": "/wiki/Isothermal_process", "Free entropy": "/wiki/Free_entropy", "Course of Theoretical Physics": "/wiki/Course_of_Theoretical_Physics", "Edit section: Nondiagonal diffusion must be nonlinear": "/w/index.php?title=Diffusion&action=edit&section=8", "Edit section: Einstein's mobility and Teorell formula": "/w/index.php?title=Diffusion&action=edit&section=9", "Einstein relation (kinetic theory)": "/wiki/Einstein_relation_(kinetic_theory)", "Drift velocity": "/wiki/Drift_velocity", "Fick's law of diffusion": "/wiki/Fick%27s_law_of_diffusion", "Boltzmann constant": "/wiki/Boltzmann_constant", "Absolute temperature": "/wiki/Absolute_temperature", "Elementary charge": "/wiki/Elementary_charge", "Avogadro constant": "/wiki/Avogadro_constant", "Mole (unit)": "/wiki/Mole_(unit)", "Activity (chemistry)": "/wiki/Activity_(chemistry)", "Edit section: Fluctuation-dissipation theorem": "/w/index.php?title=Diffusion&action=edit&section=10", "Fluctuation-dissipation theorem": "/wiki/Fluctuation-dissipation_theorem", "Langevin equation": "/wiki/Langevin_equation", "Edit section: Teorell formula for multicomponent diffusion": "/w/index.php?title=Diffusion&action=edit&section=11", "Maxwell\u2013Stefan diffusion": "/wiki/Maxwell%E2%80%93Stefan_diffusion", "Edit section: Jumps on the surface and in solids": "/w/index.php?title=Diffusion&action=edit&section=12", "Surface diffusion": "/wiki/Surface_diffusion", "Catalyst": "/wiki/Catalyst", "Edit section: Diffusion in porous media": "/w/index.php?title=Diffusion&action=edit&section=13", "Darcy's law": "/wiki/Darcy%27s_law", "Volumetric flux": "/wiki/Volumetric_flux", "Permeation": "/wiki/Permeation", "Viscosity": "/wiki/Viscosity", "Boussinesq approximation (buoyancy)": "/wiki/Boussinesq_approximation_(buoyancy)", "Yakov Borisovich Zel'dovich": "/wiki/Yakov_Borisovich_Zel%27dovich", "Edit section: Diffusion in physics": "/w/index.php?title=Diffusion&action=edit&section=14", "Edit section: Diffusion coefficient in kinetic theory of gases": "/w/index.php?title=Diffusion&action=edit&section=15", "Kinetic theory of gases": "/wiki/Kinetic_theory_of_gases#Diffusion_coefficient_and_diffusion_flux", "Amount of substance": "/wiki/Amount_of_substance", "Ideal gas law": "/wiki/Ideal_gas_law", "Edit section: The theory of diffusion in gases based on Boltzmann's equation": "/w/index.php?title=Diffusion&action=edit&section=16", "Chapman\u2013Enskog theory": "/wiki/Chapman%E2%80%93Enskog_theory", "Barodiffusion (page does not exist)": "/w/index.php?title=Barodiffusion&action=edit&redlink=1", "Thermodiffusion": "/wiki/Thermodiffusion", "Continuity equation": "/wiki/Continuity_equation", "Wendell H. Furry": "/wiki/Wendell_H._Furry", "Edit section: Diffusion of electrons in solids": "/w/index.php?title=Diffusion&action=edit&section=17", "Diffusion current": "/wiki/Diffusion_current", "Edit section: Diffusion in geophysics": "/w/index.php?title=Diffusion&action=edit&section=18", "Edit section: Dialysis": "/w/index.php?title=Diffusion&action=edit&section=19", "Hemodialysis": "/wiki/Hemodialysis", "Ultrafiltration": "/wiki/Ultrafiltration", "Semi-permeable membrane": "/wiki/Semi-permeable_membrane", "Glomerulus": "/wiki/Glomerulus", "Edit section: Random walk (random motion)": "/w/index.php?title=Diffusion&action=edit&section=20", "Edit section: Separation of diffusion from convection in gases": "/w/index.php?title=Diffusion&action=edit&section=21", "Wikipedia:Citation needed": "/wiki/Wikipedia:Citation_needed", "Heat conduction": "/wiki/Heat_conduction", "Edit section: Other types of diffusion": "/w/index.php?title=Diffusion&action=edit&section=22", "Anisotropic diffusion": "/wiki/Anisotropic_diffusion", "Atomic diffusion": "/wiki/Atomic_diffusion", "Bohm diffusion": "/wiki/Bohm_diffusion", "Eddy diffusion": "/wiki/Eddy_diffusion", "Effusion": "/wiki/Effusion", "Electronics": "/wiki/Electronics", "Current (electricity)": "/wiki/Current_(electricity)", "Facilitated diffusion": "/wiki/Facilitated_diffusion", "Gaseous diffusion": "/wiki/Gaseous_diffusion", "Isotope separation": "/wiki/Isotope_separation", "Heat equation": "/wiki/Heat_equation", "It\u014d diffusion": "/wiki/It%C5%8D_diffusion", "L\u00e9vy flight": "/wiki/L%C3%A9vy_flight", "Momentum diffusion": "/wiki/Momentum_diffusion", "Hydrodynamic": "/wiki/Hydrodynamic", "Photon diffusion": "/wiki/Photon_diffusion", "Plasma diffusion": "/wiki/Plasma_diffusion", "Reverse diffusion": "/wiki/Reverse_diffusion", "Rotational diffusion": "/wiki/Rotational_diffusion", "Taxis": "/wiki/Taxis", "Kinesis (biology)": "/wiki/Kinesis_(biology)", "Trans-cultural diffusion": "/wiki/Trans-cultural_diffusion", "Turbulent diffusion": "/wiki/Turbulent_diffusion", "Edit section: See also": "/w/index.php?title=Diffusion&action=edit&section=23", "Diffusion-limited aggregation": "/wiki/Diffusion-limited_aggregation", "Darken's equations": "/wiki/Darken%27s_equations", "Isobaric counterdiffusion": "/wiki/Isobaric_counterdiffusion", "Sorption": "/wiki/Sorption", "Osmosis": "/wiki/Osmosis", "Percolation theory": "/wiki/Percolation_theory", "Social Networks": "/wiki/Social_Networks", "Edit section: References": "/w/index.php?title=Diffusion&action=edit&section=24", "John Gamble Kirkwood": "/wiki/John_Gamble_Kirkwood", "Doi (identifier)": "/wiki/Doi_(identifier)", "ISSN (identifier)": "/wiki/ISSN_(identifier)", "PMID (identifier)": "/wiki/PMID_(identifier)", "Wayback Machine": "/wiki/Wayback_Machine", "Bibcode (identifier)": "/wiki/Bibcode_(identifier)", "ISBN (identifier)": "/wiki/ISBN_(identifier)", "Special:BookSources/978-981-12-2328-0": "/wiki/Special:BookSources/978-981-12-2328-0", "Special:BookSources/052140844X": "/wiki/Special:BookSources/052140844X", "Alexander Nikolaevich Gorban": "/wiki/Alexander_Nikolaevich_Gorban", "ArXiv (identifier)": "/wiki/ArXiv_(identifier)", "S2CID (identifier)": "/wiki/S2CID_(identifier)", "Lev Landau": "/wiki/Lev_Landau", "Evgeny Lifshitz": "/wiki/Evgeny_Lifshitz", "Butterworth-Heinemann": "/wiki/Butterworth-Heinemann", "Special:BookSources/978-0-7506-3372-7": "/wiki/Special:BookSources/978-0-7506-3372-7", "Special:BookSources/0815320515": "/wiki/Special:BookSources/0815320515", "PMC (identifier)": "/wiki/PMC_(identifier)", "Special:BookSources/0198569033": "/wiki/Special:BookSources/0198569033", "Earth Surface Processes and Landforms": "/wiki/Earth_Surface_Processes_and_Landforms", "Special:BookSources/978-0444816061": "/wiki/Special:BookSources/978-0444816061", "Help:Authority control": "/wiki/Help:Authority_control", "Edit this at Wikidata": "https://www.wikidata.org/wiki/Q163214#identifiers"}