{"Factorial experiment": "/wiki/Factorial_experiment", "Statistics": "/wiki/Statistics", "Variance": "/wiki/Variance", "Variable (mathematics)": "/wiki/Variable_(mathematics)", "Latent variable": "/wiki/Latent_variable", "Linear combination": "/wiki/Linear_combination", "Errors and residuals in statistics": "/wiki/Errors_and_residuals_in_statistics", "Errors-in-variables models": "/wiki/Errors-in-variables_models", "Psychometrics": "/wiki/Psychometrics", "Personality": "/wiki/Personality", "Marketing": "/wiki/Marketing", "Product management": "/wiki/Product_management", "Operations research": "/wiki/Operations_research", "Finance": "/wiki/Finance", "Machine learning": "/wiki/Machine_learning", "Edit section: Statistical model": "/w/index.php?title=Factor_analysis&action=edit&section=1", "Edit section: Definition": "/w/index.php?title=Factor_analysis&action=edit&section=2", "Multivariate random variable": "/wiki/Multivariate_random_variable#Expected_value", "Covariance matrix": "/wiki/Covariance_matrix", "Identity matrix": "/wiki/Identity_matrix", "Orthogonal matrix": "/wiki/Orthogonal_matrix", "Orthogonal transformation": "/wiki/Orthogonal_transformation", "Edit section: Example": "/w/index.php?title=Factor_analysis&action=edit&section=3", "Intelligence (trait)": "/wiki/Intelligence_(trait)", "Evidence": "/wiki/Evidence", "Population (statistics)": "/wiki/Population_(statistics)", "Constant (mathematics)": "/wiki/Constant_(mathematics)", "Wikipedia:Please clarify": "/wiki/Wikipedia:Please_clarify", "Astronomy": "/wiki/Astronomy", "Edit section: Mathematical model of the same example": "/w/index.php?title=Factor_analysis&action=edit&section=4", "Normalization (statistics)": "/wiki/Normalization_(statistics)", "Matrix (mathematics)": "/wiki/Matrix_(mathematics)", "Uncorrelated": "/wiki/Uncorrelated", "Kronecker delta": "/wiki/Kronecker_delta", "Generalized minimal residual method": "/wiki/Generalized_minimal_residual_method", "Skew coordinates": "/wiki/Skew_coordinates", "Edit section: Geometric interpretation": "/w/index.php?title=Factor_analysis&action=edit&section=5", "Enlarge": "/wiki/File:FactorPlot.svg", "Edit section: Practical implementation": "/w/index.php?title=Factor_analysis&action=edit&section=6", "Wikipedia:Verifiability": "/wiki/Wikipedia:Verifiability", "Help:Referencing for beginners": "/wiki/Help:Referencing_for_beginners", "Help:Maintenance template removal": "/wiki/Help:Maintenance_template_removal", "Edit section: Types of factor analysis": "/w/index.php?title=Factor_analysis&action=edit&section=7", "Edit section: Exploratory factor analysis": "/w/index.php?title=Factor_analysis&action=edit&section=8", "Exploratory factor analysis": "/wiki/Exploratory_factor_analysis", "Edit section: Confirmatory factor analysis": "/w/index.php?title=Factor_analysis&action=edit&section=9", "Confirmatory factor analysis": "/wiki/Confirmatory_factor_analysis", "Structural equation modeling": "/wiki/Structural_equation_modeling", "Least-squares estimation": "/wiki/Least-squares_estimation", "Edit section: Types of factor extraction": "/w/index.php?title=Factor_analysis&action=edit&section=10", "Principal component analysis": "/wiki/Principal_component_analysis", "Principal factor analysis": "/wiki/Principal_factor_analysis", "Correlation matrix": "/wiki/Correlation_matrix", "Multiple regression": "/wiki/Multiple_regression", "Edit section: Terminology": "/w/index.php?title=Factor_analysis&action=edit&section=11", "Pearson product-moment correlation coefficient": "/wiki/Pearson_product-moment_correlation_coefficient", "Eigenvalue": "/wiki/Eigenvalue", "Angle": "/wiki/Angle#Types_of_angles", "Coefficient": "/wiki/Coefficient", "Edit section: Criteria for determining the number of factors": "/w/index.php?title=Factor_analysis&action=edit&section=12", "Parallel analysis": "/wiki/Parallel_analysis", "Edit section: Modern criteria": "/w/index.php?title=Factor_analysis&action=edit&section=13", "Horn's parallel analysis": "/wiki/Horn%27s_parallel_analysis", "R (programming language)": "/wiki/R_(programming_language)", "Anton Formann": "/wiki/Anton_Formann", "Sample size": "/wiki/Sample_size", "Item response theory": "/wiki/Item_response_theory#The_item_response_function", "Correlation coefficient": "/wiki/Correlation_coefficient", "Edit section: Older methods": "/w/index.php?title=Factor_analysis&action=edit&section=14", "SPSS": "/wiki/SPSS", "Statistical software": "/wiki/Statistical_software", "Confidence interval": "/wiki/Confidence_interval", "Scree plot": "/wiki/Scree_plot", "Y-axis": "/wiki/Y-axis", "wiktionary:fudge factor": "https://en.wiktionary.org/wiki/fudge_factor", "Wikipedia:Citation needed": "/wiki/Wikipedia:Citation_needed", "Occam's razor": "/wiki/Occam%27s_razor", "Edit section: Bayesian method": "/w/index.php?title=Factor_analysis&action=edit&section=15", "Indian buffet process": "/wiki/Indian_buffet_process", "Probability distribution": "/wiki/Probability_distribution", "Edit section: Rotation methods": "/w/index.php?title=Factor_analysis&action=edit&section=16", "Orthogonal": "/wiki/Orthogonal", "Correlation": "/wiki/Correlation", "Rotation (mathematics)": "/wiki/Rotation_(mathematics)", "Coordinate system": "/wiki/Coordinate_system", "Varimax rotation": "/wiki/Varimax_rotation", "Dataset": "/wiki/Dataset", "Edit section: Problems with factor rotation": "/w/index.php?title=Factor_analysis&action=edit&section=17", "Edit section: Higher order factor analysis": "/w/index.php?title=Factor_analysis&action=edit&section=18", "Wikipedia:Vagueness": "/wiki/Wikipedia:Vagueness", "Talk:Factor analysis": "/wiki/Talk:Factor_analysis", "Oblique rotation (page does not exist)": "/w/index.php?title=Oblique_rotation&action=edit&redlink=1", "Matrix multiplication": "/wiki/Matrix_multiplication", "Factor pattern matrix (page does not exist)": "/w/index.php?title=Factor_pattern_matrix&action=edit&redlink=1", "Statistical dispersion": "/wiki/Statistical_dispersion", "Edit section: Exploratory factor analysis (EFA) versus principal components analysis (PCA)": "/w/index.php?title=Factor_analysis&action=edit&section=19", "Eigenvalues": "/wiki/Eigenvalues", "Edit section: Arguments contrasting PCA and EFA": "/w/index.php?title=Factor_analysis&action=edit&section=20", "Correlation and dependence": "/wiki/Correlation_and_dependence", "Edit section: Variance versus covariance": "/w/index.php?title=Factor_analysis&action=edit&section=21", "Random error": "/wiki/Random_error", "Edit section: Differences in procedure and results": "/w/index.php?title=Factor_analysis&action=edit&section=22", "Eigenvalues and eigenvectors": "/wiki/Eigenvalues_and_eigenvectors", "Edit section: In psychometrics": "/w/index.php?title=Factor_analysis&action=edit&section=23", "Edit section: History": "/w/index.php?title=Factor_analysis&action=edit&section=24", "Charles Spearman": "/wiki/Charles_Spearman", "G factor (psychometrics)": "/wiki/G_factor_(psychometrics)", "Louis Leon Thurstone": "/wiki/Louis_Leon_Thurstone", "The Vectors of Mind": "/wiki/The_Vectors_of_Mind", "Q methodology": "/wiki/Q_methodology", "Raymond Cattell": "/wiki/Raymond_Cattell", "Edit section: Applications in psychology": "/w/index.php?title=Factor_analysis&action=edit&section=25", "Edit section: Advantages": "/w/index.php?title=Factor_analysis&action=edit&section=26", "Three Stratum Theory": "/wiki/Three_Stratum_Theory", "Edit section: Disadvantages": "/w/index.php?title=Factor_analysis&action=edit&section=27", "Edit section: In cross-cultural research": "/w/index.php?title=Factor_analysis&action=edit&section=28", "Hofstede's cultural dimensions theory": "/wiki/Hofstede%27s_cultural_dimensions_theory", "Geert Hofstede": "/wiki/Geert_Hofstede", "Ronald Inglehart": "/wiki/Ronald_Inglehart", "Christian Welzel": "/wiki/Christian_Welzel", "Shalom H. Schwartz": "/wiki/Shalom_H._Schwartz", "Inglehart\u2013Welzel cultural map of the world": "/wiki/Inglehart%E2%80%93Welzel_cultural_map_of_the_world", "Edit section: In political science": "/w/index.php?title=Factor_analysis&action=edit&section=29", "United States presidential debates": "/wiki/United_States_presidential_debates", "Hillary Clinton email controversy": "/wiki/Hillary_Clinton_email_controversy", "FiveThirtyEight": "/wiki/FiveThirtyEight", "Prediction market": "/wiki/Prediction_market", "Edit section: In marketing": "/w/index.php?title=Factor_analysis&action=edit&section=30", "Product (business)": "/wiki/Product_(business)", "Quantitative marketing research": "/wiki/Quantitative_marketing_research", "Statistical survey": "/wiki/Statistical_survey", "Customer": "/wiki/Customer", "Perceptual mapping": "/wiki/Perceptual_mapping", "Positioning (marketing)": "/wiki/Positioning_(marketing)", "Edit section: Information collection": "/w/index.php?title=Factor_analysis&action=edit&section=31", "SAS System": "/wiki/SAS_System", "Stata": "/wiki/Stata", "STATISTICA": "/wiki/STATISTICA", "Edit section: Analysis": "/w/index.php?title=Factor_analysis&action=edit&section=32", "Edit section: In physical and biological sciences": "/w/index.php?title=Factor_analysis&action=edit&section=35", "Geochemistry": "/wiki/Geochemistry", "Hydrochemistry": "/wiki/Hydrochemistry", "Astrophysics": "/wiki/Astrophysics", "Cosmology": "/wiki/Cosmology", "Ecology": "/wiki/Ecology", "Molecular biology": "/wiki/Molecular_biology", "Neuroscience": "/wiki/Neuroscience", "Biochemistry": "/wiki/Biochemistry", "Edit section: In microarray analysis": "/w/index.php?title=Factor_analysis&action=edit&section=36", "Oligonucleotide": "/wiki/Oligonucleotide", "DNA microarrays": "/wiki/DNA_microarrays", "Affymetrix": "/wiki/Affymetrix", "RNA": "/wiki/RNA", "Edit section: Implementation": "/w/index.php?title=Factor_analysis&action=edit&section=37", "BMDP": "/wiki/BMDP", "JMP (statistical software)": "/wiki/JMP_(statistical_software)", "Mplus (page does not exist)": "/w/index.php?title=Mplus&action=edit&redlink=1", "Python (programming language)": "/wiki/Python_(programming_language)", "Scikit-learn": "/wiki/Scikit-learn", "SAS (software)": "/wiki/SAS_(software)", "Edit section: Stand-alone": "/w/index.php?title=Factor_analysis&action=edit&section=38", "Rovira i Virgili University": "/wiki/Rovira_i_Virgili_University", "Edit section: See also": "/w/index.php?title=Factor_analysis&action=edit&section=39", "Portal:Mathematics": "/wiki/Portal:Mathematics", "Design of experiments": "/wiki/Design_of_experiments", "Formal concept analysis": "/wiki/Formal_concept_analysis", "Independent component analysis": "/wiki/Independent_component_analysis", "Non-negative matrix factorization": "/wiki/Non-negative_matrix_factorization", "Recommendation system": "/wiki/Recommendation_system", "Root cause analysis": "/wiki/Root_cause_analysis", "Facet theory": "/wiki/Facet_theory", "Edit section: Notes": "/w/index.php?title=Factor_analysis&action=edit&section=40", "Edit section: References": "/w/index.php?title=Factor_analysis&action=edit&section=41", "Karl Gustav J\u00f6reskog": "/wiki/Karl_Gustav_J%C3%B6reskog", "ISBN (identifier)": "/wiki/ISBN_(identifier)", "Special:BookSources/0-89859-277-1": "/wiki/Special:BookSources/0-89859-277-1", "Special:BookSources/978-0-226-31652-9": "/wiki/Special:BookSources/978-0-226-31652-9", "Bibcode (identifier)": "/wiki/Bibcode_(identifier)", "Doi (identifier)": "/wiki/Doi_(identifier)", "S2CID (identifier)": "/wiki/S2CID_(identifier)", "PMID (identifier)": "/wiki/PMID_(identifier)", "ArXiv (identifier)": "/wiki/ArXiv_(identifier)", "Template:Cite journal": "/wiki/Template:Cite_journal", "Help:CS1 errors": "/wiki/Help:CS1_errors#missing_periodical", "Special:BookSources/978-0-8058-6237-9": "/wiki/Special:BookSources/978-0-8058-6237-9", "Special:BookSources/978-1584889601": "/wiki/Special:BookSources/978-1584889601", "Special:BookSources/978-0-387-95442-4": "/wiki/Special:BookSources/978-0-387-95442-4", "Special:BookSources/978-1-4200-9961-4": "/wiki/Special:BookSources/978-1-4200-9961-4", "JSTOR (identifier)": "/wiki/JSTOR_(identifier)", "Special:BookSources/978-0-8058-6212-6": "/wiki/Special:BookSources/978-0-8058-6212-6", "Special:BookSources/9781452242194": "/wiki/Special:BookSources/9781452242194", "OCLC (identifier)": "/wiki/OCLC_(identifier)", "ISSN (identifier)": "/wiki/ISSN_(identifier)", "Edit section: Further reading": "/w/index.php?title=Factor_analysis&action=edit&section=42", "Continuum International": "/wiki/Continuum_International", "Special:BookSources/978-0-8264-8000-2": "/wiki/Special:BookSources/978-0-8264-8000-2", "Stanley A. Mulaik": "/wiki/Stanley_A._Mulaik", "Chapman & Hall": "/wiki/Chapman_%26_Hall", "Hdl (identifier)": "/wiki/Hdl_(identifier)", "American Psychological Association": "/wiki/American_Psychological_Association", "Special:BookSources/978-1591470939": "/wiki/Special:BookSources/978-1591470939", "Edit section: External links": "/w/index.php?title=Factor_analysis&action=edit&section=43", "commons:Category:Factor analysis": "https://commons.wikimedia.org/wiki/Category:Factor_analysis", "Wayback Machine": "/wiki/Wayback_Machine", "Template:Statistics": "/wiki/Template:Statistics", "Template talk:Statistics": "/wiki/Template_talk:Statistics", "Outline of statistics": "/wiki/Outline_of_statistics", "List of statistics articles": "/wiki/List_of_statistics_articles", "Descriptive statistics": "/wiki/Descriptive_statistics", "Continuous probability distribution": "/wiki/Continuous_probability_distribution", "Central tendency": "/wiki/Central_tendency", "Mean": "/wiki/Mean", "Arithmetic mean": "/wiki/Arithmetic_mean", "Arithmetic\u2013geometric mean": "/wiki/Arithmetic%E2%80%93geometric_mean", "Cubic mean": "/wiki/Cubic_mean", "Generalized mean": "/wiki/Generalized_mean", "Geometric mean": "/wiki/Geometric_mean", "Harmonic mean": "/wiki/Harmonic_mean", "Heronian mean": "/wiki/Heronian_mean", "Heinz mean": "/wiki/Heinz_mean", "Lehmer mean": "/wiki/Lehmer_mean", "Median": "/wiki/Median", "Mode (statistics)": "/wiki/Mode_(statistics)", "Average absolute deviation": "/wiki/Average_absolute_deviation", "Coefficient of variation": "/wiki/Coefficient_of_variation", "Interquartile range": "/wiki/Interquartile_range", "Percentile": "/wiki/Percentile", "Range (statistics)": "/wiki/Range_(statistics)", "Standard deviation": "/wiki/Standard_deviation", "Shape of the distribution": "/wiki/Shape_of_the_distribution", "Central limit theorem": "/wiki/Central_limit_theorem", "Moment (mathematics)": "/wiki/Moment_(mathematics)", "Kurtosis": "/wiki/Kurtosis", "L-moment": "/wiki/L-moment", "Skewness": "/wiki/Skewness", "Count data": "/wiki/Count_data", "Index of dispersion": "/wiki/Index_of_dispersion", "Contingency table": "/wiki/Contingency_table", "Frequency distribution": "/wiki/Frequency_distribution", "Grouped data": "/wiki/Grouped_data", "Partial correlation": "/wiki/Partial_correlation", "Pearson correlation coefficient": "/wiki/Pearson_correlation_coefficient", "Rank correlation": "/wiki/Rank_correlation", "Kendall rank correlation coefficient": "/wiki/Kendall_rank_correlation_coefficient", "Spearman's rank correlation coefficient": "/wiki/Spearman%27s_rank_correlation_coefficient", "Scatter plot": "/wiki/Scatter_plot", "Statistical graphics": "/wiki/Statistical_graphics", "Bar chart": "/wiki/Bar_chart", "Biplot": "/wiki/Biplot", "Box plot": "/wiki/Box_plot", "Control chart": "/wiki/Control_chart", "Correlogram": "/wiki/Correlogram", "Fan chart (statistics)": "/wiki/Fan_chart_(statistics)", "Forest plot": "/wiki/Forest_plot", "Histogram": "/wiki/Histogram", "Pie chart": "/wiki/Pie_chart", "Q\u2013Q plot": "/wiki/Q%E2%80%93Q_plot", "Radar chart": "/wiki/Radar_chart", "Run chart": "/wiki/Run_chart", "Stem-and-leaf display": "/wiki/Stem-and-leaf_display", "Violin plot": "/wiki/Violin_plot", "Data collection": "/wiki/Data_collection", "Effect size": "/wiki/Effect_size", "Missing data": "/wiki/Missing_data", "Optimal design": "/wiki/Optimal_design", "Statistical population": "/wiki/Statistical_population", "Replication (statistics)": "/wiki/Replication_(statistics)", "Sample size determination": "/wiki/Sample_size_determination", "Statistic": "/wiki/Statistic", "Statistical power": "/wiki/Statistical_power", "Survey methodology": "/wiki/Survey_methodology", "Sampling (statistics)": "/wiki/Sampling_(statistics)", "Cluster sampling": "/wiki/Cluster_sampling", "Stratified sampling": "/wiki/Stratified_sampling", "Opinion poll": "/wiki/Opinion_poll", "Questionnaire": "/wiki/Questionnaire", "Standard error": "/wiki/Standard_error", "Experiment": "/wiki/Experiment", "Blocking (statistics)": "/wiki/Blocking_(statistics)", "Interaction (statistics)": "/wiki/Interaction_(statistics)", "Random assignment": "/wiki/Random_assignment", "Randomized controlled trial": "/wiki/Randomized_controlled_trial", "Randomized experiment": "/wiki/Randomized_experiment", "Scientific control": "/wiki/Scientific_control", "Adaptive clinical trial": "/wiki/Adaptive_clinical_trial", "Stochastic approximation": "/wiki/Stochastic_approximation", "Up-and-Down Designs": "/wiki/Up-and-Down_Designs", "Observational study": "/wiki/Observational_study", "Cohort study": "/wiki/Cohort_study", "Cross-sectional study": "/wiki/Cross-sectional_study", "Natural experiment": "/wiki/Natural_experiment", "Quasi-experiment": "/wiki/Quasi-experiment", "Statistical inference": "/wiki/Statistical_inference", "Statistical theory": "/wiki/Statistical_theory", "Sampling distribution": "/wiki/Sampling_distribution", "Order statistic": "/wiki/Order_statistic", "Empirical distribution function": "/wiki/Empirical_distribution_function", "Density estimation": "/wiki/Density_estimation", "Statistical model": "/wiki/Statistical_model", "Model specification": "/wiki/Model_specification", "Lp space": "/wiki/Lp_space", "Statistical parameter": "/wiki/Statistical_parameter", "Location parameter": "/wiki/Location_parameter", "Scale parameter": "/wiki/Scale_parameter", "Shape parameter": "/wiki/Shape_parameter", "Parametric statistics": "/wiki/Parametric_statistics", "Likelihood function": "/wiki/Likelihood_function", "Monotone likelihood ratio": "/wiki/Monotone_likelihood_ratio", "Location\u2013scale family": "/wiki/Location%E2%80%93scale_family", "Exponential family": "/wiki/Exponential_family", "Completeness (statistics)": "/wiki/Completeness_(statistics)", "Sufficient statistic": "/wiki/Sufficient_statistic", "Plug-in principle": "/wiki/Plug-in_principle", "Bootstrapping (statistics)": "/wiki/Bootstrapping_(statistics)", "U-statistic": "/wiki/U-statistic", "V-statistic": "/wiki/V-statistic", "Optimal decision": "/wiki/Optimal_decision", "Loss function": "/wiki/Loss_function", "Efficiency (statistics)": "/wiki/Efficiency_(statistics)", "Statistical distance": "/wiki/Statistical_distance", "Divergence (statistics)": "/wiki/Divergence_(statistics)", "Asymptotic theory (statistics)": "/wiki/Asymptotic_theory_(statistics)", "Robust statistics": "/wiki/Robust_statistics", "Frequentist inference": "/wiki/Frequentist_inference", "Point estimation": "/wiki/Point_estimation", "Estimating equations": "/wiki/Estimating_equations", "Maximum likelihood": "/wiki/Maximum_likelihood", "Method of moments (statistics)": "/wiki/Method_of_moments_(statistics)", "M-estimator": "/wiki/M-estimator", "Minimum distance estimation": "/wiki/Minimum_distance_estimation", "Bias of an estimator": "/wiki/Bias_of_an_estimator", "Minimum-variance unbiased estimator": "/wiki/Minimum-variance_unbiased_estimator", "Rao\u2013Blackwell theorem": "/wiki/Rao%E2%80%93Blackwell_theorem", "Lehmann\u2013Scheff\u00e9 theorem": "/wiki/Lehmann%E2%80%93Scheff%C3%A9_theorem", "Median-unbiased estimator": "/wiki/Median-unbiased_estimator", "Interval estimation": "/wiki/Interval_estimation", "Pivotal quantity": "/wiki/Pivotal_quantity", "Likelihood interval": "/wiki/Likelihood_interval", "Prediction interval": "/wiki/Prediction_interval", "Tolerance interval": "/wiki/Tolerance_interval", "Resampling (statistics)": "/wiki/Resampling_(statistics)", "Jackknife resampling": "/wiki/Jackknife_resampling", "Statistical hypothesis testing": "/wiki/Statistical_hypothesis_testing", "One- and two-tailed tests": "/wiki/One-_and_two-tailed_tests", "Power (statistics)": "/wiki/Power_(statistics)", "Uniformly most powerful test": "/wiki/Uniformly_most_powerful_test", "Permutation test": "/wiki/Permutation_test", "Randomization test": "/wiki/Randomization_test", "Multiple comparisons": "/wiki/Multiple_comparisons", "Likelihood-ratio test": "/wiki/Likelihood-ratio_test", "Score test": "/wiki/Score_test", "Wald test": "/wiki/Wald_test", "Z-test": "/wiki/Z-test", "Student's t-test": "/wiki/Student%27s_t-test", "F-test": "/wiki/F-test", "Goodness of fit": "/wiki/Goodness_of_fit", "Chi-squared test": "/wiki/Chi-squared_test", "G-test": "/wiki/G-test", "Kolmogorov\u2013Smirnov test": "/wiki/Kolmogorov%E2%80%93Smirnov_test", "Anderson\u2013Darling test": "/wiki/Anderson%E2%80%93Darling_test", "Lilliefors test": "/wiki/Lilliefors_test", "Jarque\u2013Bera test": "/wiki/Jarque%E2%80%93Bera_test", "Shapiro\u2013Wilk test": "/wiki/Shapiro%E2%80%93Wilk_test", "Model selection": "/wiki/Model_selection", "Cross-validation (statistics)": "/wiki/Cross-validation_(statistics)", "Akaike information criterion": "/wiki/Akaike_information_criterion", "Bayesian information criterion": "/wiki/Bayesian_information_criterion", "Rank statistics": "/wiki/Rank_statistics", "Sign test": "/wiki/Sign_test", "Sample median": "/wiki/Sample_median", "Wilcoxon signed-rank test": "/wiki/Wilcoxon_signed-rank_test", "Hodges\u2013Lehmann estimator": "/wiki/Hodges%E2%80%93Lehmann_estimator", "Mann\u2013Whitney U test": "/wiki/Mann%E2%80%93Whitney_U_test", "Nonparametric statistics": "/wiki/Nonparametric_statistics", "Analysis of variance": "/wiki/Analysis_of_variance", "Kruskal\u2013Wallis one-way analysis of variance": "/wiki/Kruskal%E2%80%93Wallis_one-way_analysis_of_variance", "Friedman test": "/wiki/Friedman_test", "Jonckheere's trend test": "/wiki/Jonckheere%27s_trend_test", "Van der Waerden test": "/wiki/Van_der_Waerden_test", "Bayesian inference": "/wiki/Bayesian_inference", "Bayesian probability": "/wiki/Bayesian_probability", "Prior probability": "/wiki/Prior_probability", "Posterior probability": "/wiki/Posterior_probability", "Credible interval": "/wiki/Credible_interval", "Bayes factor": "/wiki/Bayes_factor", "Bayes estimator": "/wiki/Bayes_estimator", "Maximum a posteriori estimation": "/wiki/Maximum_a_posteriori_estimation", "Regression analysis": "/wiki/Regression_analysis", "Confounding": "/wiki/Confounding", "Coefficient of determination": "/wiki/Coefficient_of_determination", "Errors and residuals": "/wiki/Errors_and_residuals", "Regression validation": "/wiki/Regression_validation", "Mixed model": "/wiki/Mixed_model", "Simultaneous equations model": "/wiki/Simultaneous_equations_model", "Multivariate adaptive regression splines": "/wiki/Multivariate_adaptive_regression_splines", "Linear regression": "/wiki/Linear_regression", "Simple linear regression": "/wiki/Simple_linear_regression", "Ordinary least squares": "/wiki/Ordinary_least_squares", "General linear model": "/wiki/General_linear_model", "Bayesian linear regression": "/wiki/Bayesian_linear_regression", "Nonlinear regression": "/wiki/Nonlinear_regression", "Nonparametric regression": "/wiki/Nonparametric_regression", "Semiparametric regression": "/wiki/Semiparametric_regression", "Isotonic regression": "/wiki/Isotonic_regression", "Robust regression": "/wiki/Robust_regression", "Heteroscedasticity": "/wiki/Heteroscedasticity", "Homoscedasticity": "/wiki/Homoscedasticity", "Generalized linear model": "/wiki/Generalized_linear_model", "Logistic regression": "/wiki/Logistic_regression", "Binomial regression": "/wiki/Binomial_regression", "Poisson regression": "/wiki/Poisson_regression", "Partition of sums of squares": "/wiki/Partition_of_sums_of_squares", "Analysis of covariance": "/wiki/Analysis_of_covariance", "Multivariate analysis of variance": "/wiki/Multivariate_analysis_of_variance", "Degrees of freedom (statistics)": "/wiki/Degrees_of_freedom_(statistics)", "Categorical variable": "/wiki/Categorical_variable", "Multivariate statistics": "/wiki/Multivariate_statistics", "Time series": "/wiki/Time_series", "Survival analysis": "/wiki/Survival_analysis", "Cohen's kappa": "/wiki/Cohen%27s_kappa", "Graphical model": "/wiki/Graphical_model", "McNemar's test": "/wiki/McNemar%27s_test", "Cochran\u2013Mantel\u2013Haenszel statistics": "/wiki/Cochran%E2%80%93Mantel%E2%80%93Haenszel_statistics", "Canonical correlation": "/wiki/Canonical_correlation", "Linear discriminant analysis": "/wiki/Linear_discriminant_analysis", "Cluster analysis": "/wiki/Cluster_analysis", "Statistical classification": "/wiki/Statistical_classification", "Multivariate distribution": "/wiki/Multivariate_distribution", "Elliptical distribution": "/wiki/Elliptical_distribution", "Multivariate normal distribution": "/wiki/Multivariate_normal_distribution", "Decomposition of time series": "/wiki/Decomposition_of_time_series", "Trend estimation": "/wiki/Trend_estimation", "Stationary process": "/wiki/Stationary_process", "Seasonal adjustment": "/wiki/Seasonal_adjustment", "Exponential smoothing": "/wiki/Exponential_smoothing", "Cointegration": "/wiki/Cointegration", "Structural break": "/wiki/Structural_break", "Granger causality": "/wiki/Granger_causality", "Dickey\u2013Fuller test": "/wiki/Dickey%E2%80%93Fuller_test", "Johansen test": "/wiki/Johansen_test", "Ljung\u2013Box test": "/wiki/Ljung%E2%80%93Box_test", "Durbin\u2013Watson statistic": "/wiki/Durbin%E2%80%93Watson_statistic", "Breusch\u2013Godfrey test": "/wiki/Breusch%E2%80%93Godfrey_test", "Time domain": "/wiki/Time_domain", "Autocorrelation": "/wiki/Autocorrelation", "Partial autocorrelation function": "/wiki/Partial_autocorrelation_function", "Cross-correlation": "/wiki/Cross-correlation", "Autoregressive\u2013moving-average model": "/wiki/Autoregressive%E2%80%93moving-average_model", "Box\u2013Jenkins method": "/wiki/Box%E2%80%93Jenkins_method", "Autoregressive conditional heteroskedasticity": "/wiki/Autoregressive_conditional_heteroskedasticity", "Vector autoregression": "/wiki/Vector_autoregression", "Frequency domain": "/wiki/Frequency_domain", "Spectral density estimation": "/wiki/Spectral_density_estimation", "Fourier analysis": "/wiki/Fourier_analysis", "Least-squares spectral analysis": "/wiki/Least-squares_spectral_analysis", "Wavelet": "/wiki/Wavelet", "Whittle likelihood": "/wiki/Whittle_likelihood", "Survival function": "/wiki/Survival_function", "Kaplan\u2013Meier estimator": "/wiki/Kaplan%E2%80%93Meier_estimator", "Proportional hazards model": "/wiki/Proportional_hazards_model", "Accelerated failure time model": "/wiki/Accelerated_failure_time_model", "First-hitting-time model": "/wiki/First-hitting-time_model", "Failure rate": "/wiki/Failure_rate", "Nelson\u2013Aalen estimator": "/wiki/Nelson%E2%80%93Aalen_estimator", "Log-rank test": "/wiki/Log-rank_test", "List of fields of application of statistics": "/wiki/List_of_fields_of_application_of_statistics", "Biostatistics": "/wiki/Biostatistics", "Bioinformatics": "/wiki/Bioinformatics", "Clinical trial": "/wiki/Clinical_trial", "Clinical study design": "/wiki/Clinical_study_design", "Epidemiology": "/wiki/Epidemiology", "Medical statistics": "/wiki/Medical_statistics", "Engineering statistics": "/wiki/Engineering_statistics", "Chemometrics": "/wiki/Chemometrics", "Methods engineering": "/wiki/Methods_engineering", "Probabilistic design": "/wiki/Probabilistic_design", "Statistical process control": "/wiki/Statistical_process_control", "Quality control": "/wiki/Quality_control", "Reliability engineering": "/wiki/Reliability_engineering", "System identification": "/wiki/System_identification", "Social statistics": "/wiki/Social_statistics", "Actuarial science": "/wiki/Actuarial_science", "Census": "/wiki/Census", "Crime statistics": "/wiki/Crime_statistics", "Demographic statistics": "/wiki/Demographic_statistics", "Econometrics": "/wiki/Econometrics", "Jurimetrics": "/wiki/Jurimetrics", "National accounts": "/wiki/National_accounts", "Official statistics": "/wiki/Official_statistics", "Population statistics": "/wiki/Population_statistics", "Spatial analysis": "/wiki/Spatial_analysis", "Cartography": "/wiki/Cartography", "Environmental statistics": "/wiki/Environmental_statistics", "Geographic information system": "/wiki/Geographic_information_system", "Geostatistics": "/wiki/Geostatistics", "Kriging": "/wiki/Kriging", "Category:Statistics": "/wiki/Category:Statistics", "commons:Category:Statistics": "https://commons.wikimedia.org/wiki/Category:Statistics", "Wikipedia:WikiProject Statistics": "/wiki/Wikipedia:WikiProject_Statistics"}