{"Computer science": "/wiki/Computer_science", "Formal grammar": "/wiki/Formal_grammar#Analytic_grammars", "Formal language": "/wiki/Formal_language", "String (computer science)": "/wiki/String_(computer_science)", "Top-down parsing language": "/wiki/Top-down_parsing_language", "Context-free grammar": "/wiki/Context-free_grammar", "Recursive descent parser": "/wiki/Recursive_descent_parser", "Ambiguous grammar": "/wiki/Ambiguous_grammar", "Parse tree": "/wiki/Parse_tree", "Lojban": "/wiki/Lojban", "Natural language": "/wiki/Natural_language", "Earley algorithm": "/wiki/Earley_algorithm", "Edit section: Definition": "/w/index.php?title=Parsing_expression_grammar&action=edit&section=1", "Wikipedia:Citing sources": "/wiki/Wikipedia:Citing_sources", "Wikipedia:Further reading": "/wiki/Wikipedia:Further_reading", "Wikipedia:External links": "/wiki/Wikipedia:External_links", "Wikipedia:WikiProject Fact and Reference Check": "/wiki/Wikipedia:WikiProject_Fact_and_Reference_Check", "Wikipedia:When to cite": "/wiki/Wikipedia:When_to_cite", "Help:Maintenance template removal": "/wiki/Help:Maintenance_template_removal", "Edit section: Syntax": "/w/index.php?title=Parsing_expression_grammar&action=edit&section=2", "Nonterminal symbol": "/wiki/Nonterminal_symbol", "Terminal symbol": "/wiki/Terminal_symbol", "Disjoint sets": "/wiki/Disjoint_sets", "Expression (mathematics)": "/wiki/Expression_(mathematics)", "Regular expression": "/wiki/Regular_expression", "Edit section: Semantics": "/w/index.php?title=Parsing_expression_grammar&action=edit&section=3", "Context-free grammars": "/wiki/Context-free_grammars", "Commutativity": "/wiki/Commutativity", "Cut (logic programming)": "/wiki/Cut_(logic_programming)", "Logic programming": "/wiki/Logic_programming", "Boolean grammar": "/wiki/Boolean_grammar", "Syntactic predicate": "/wiki/Syntactic_predicate", "Parsing": "/wiki/Parsing#Lookahead", "Edit section: Operational interpretation of parsing expressions": "/w/index.php?title=Parsing_expression_grammar&action=edit&section=4", "Function (mathematics)": "/wiki/Function_(mathematics)", "Recursion": "/wiki/Recursion", "Backtracking": "/wiki/Backtracking", "Greedy algorithm": "/wiki/Greedy_algorithm", "Edit section: Examples": "/w/index.php?title=Parsing_expression_grammar&action=edit&section=5", "Dangling else": "/wiki/Dangling_else", "Context-free language": "/wiki/Context-free_language", "Edit section: Implementing parsers from parsing expression grammars": "/w/index.php?title=Parsing_expression_grammar&action=edit&section=6", "Exponential time": "/wiki/Exponential_time", "Linear time": "/wiki/Linear_time", "Memoization": "/wiki/Memoization", "Mutual recursion": "/wiki/Mutual_recursion", "LL parser": "/wiki/LL_parser", "LR parser": "/wiki/LR_parser", "Edit section: Advantages": "/w/index.php?title=Parsing_expression_grammar&action=edit&section=7", "Regular expressions": "/wiki/Regular_expressions", "Edit section: Disadvantages": "/w/index.php?title=Parsing_expression_grammar&action=edit&section=8", "Edit section: Memory consumption": "/w/index.php?title=Parsing_expression_grammar&action=edit&section=9", "Graph algorithms": "/wiki/Graph_algorithms", "Bellman\u2013Ford algorithm": "/wiki/Bellman%E2%80%93Ford_algorithm", "Floyd\u2013Warshall algorithm": "/wiki/Floyd%E2%80%93Warshall_algorithm", "Edit section: Indirect left recursion": "/w/index.php?title=Parsing_expression_grammar&action=edit&section=10", "Left recursion": "/wiki/Left_recursion", "Circular definition": "/wiki/Circular_definition", "OMeta": "/wiki/OMeta", "GLR parser": "/wiki/GLR_parser", "Edit section: Expressive power": "/w/index.php?title=Parsing_expression_grammar&action=edit&section=11", "LL(k)": "/wiki/LL(k)", "CYK algorithm": "/wiki/CYK_algorithm", "Edit section: Ambiguity detection and influence of rule order on language that is matched": "/w/index.php?title=Parsing_expression_grammar&action=edit&section=12", "Edit section: Bottom-up PEG parsing": "/w/index.php?title=Parsing_expression_grammar&action=edit&section=13", "Edit section: Practical use": "/w/index.php?title=Parsing_expression_grammar&action=edit&section=14", "Python (programming language)": "/wiki/Python_(programming_language)", "CPython": "/wiki/CPython", "Jq (programming language)": "/wiki/Jq_(programming_language)#Parsing_Expression_Grammars", "Edit section: See also": "/w/index.php?title=Parsing_expression_grammar&action=edit&section=15", "Compiler Description Language": "/wiki/Compiler_Description_Language", "Comparison of parser generators": "/wiki/Comparison_of_parser_generators", "Parser combinator": "/wiki/Parser_combinator", "Edit section: References": "/w/index.php?title=Parsing_expression_grammar&action=edit&section=16", "Association for Computing Machinery": "/wiki/Association_for_Computing_Machinery", "Doi (identifier)": "/wiki/Doi_(identifier)", "ISBN (identifier)": "/wiki/ISBN_(identifier)", "Special:BookSources/1-58113-729-X": "/wiki/Special:BookSources/1-58113-729-X", "Addison-Wesley Longman": "/wiki/Addison-Wesley_Longman", "Special:BookSources/0-201-10088-6": "/wiki/Special:BookSources/0-201-10088-6", "Special:BookSources/9781595939777": "/wiki/Special:BookSources/9781595939777", "ArXiv (identifier)": "/wiki/ArXiv_(identifier)", "Edit section: External links": "/w/index.php?title=Parsing_expression_grammar&action=edit&section=17", "Constructed language": "/wiki/Constructed_language", "Template:Parsers": "/wiki/Template:Parsers", "Template talk:Parsers": "/wiki/Template_talk:Parsers", "Top-down parsing": "/wiki/Top-down_parsing", "Tail recursive parser": "/wiki/Tail_recursive_parser", "Bottom-up parsing": "/wiki/Bottom-up_parsing", "Simple precedence parser": "/wiki/Simple_precedence_parser", "Operator-precedence parser": "/wiki/Operator-precedence_parser", "Shunting yard algorithm": "/wiki/Shunting_yard_algorithm", "Simple LR parser": "/wiki/Simple_LR_parser", "LALR parser": "/wiki/LALR_parser", "Canonical LR parser": "/wiki/Canonical_LR_parser", "Recursive ascent parser": "/wiki/Recursive_ascent_parser", "Shift-reduce parser": "/wiki/Shift-reduce_parser", "Chart parser": "/wiki/Chart_parser", "Earley parser": "/wiki/Earley_parser", "Definite clause grammar": "/wiki/Definite_clause_grammar", "Deterministic parsing": "/wiki/Deterministic_parsing", "Dynamic programming": "/wiki/Dynamic_programming", "Compiler-compiler": "/wiki/Compiler-compiler", "LALR parser generator": "/wiki/LALR_parser_generator", "Abstract syntax tree": "/wiki/Abstract_syntax_tree", "Scannerless parsing": "/wiki/Scannerless_parsing", "History of compiler construction": "/wiki/History_of_compiler_construction", "Operator-precedence grammar": "/wiki/Operator-precedence_grammar"}