{"Computer science": "/wiki/Computer_science", "Algorithm": "/wiki/Algorithm", "Concurrent computing": "/wiki/Concurrent_computing", "Parallel computing": "/wiki/Parallel_computing", "Concurrent algorithm": "/wiki/Concurrent_algorithm", "Parallel algorithm": "/wiki/Parallel_algorithm", "Distributed algorithm": "/wiki/Distributed_algorithm", "Convolutional code": "/wiki/Convolutional_code", "Edit section: See also": "/w/index.php?title=Sequential_algorithm&action=edit&section=1", "Online algorithm": "/wiki/Online_algorithm", "Streaming algorithm": "/wiki/Streaming_algorithm", "Edit section: References": "/w/index.php?title=Sequential_algorithm&action=edit&section=2", "Data structure": "/wiki/Data_structure", "Wikipedia:Stub": "/wiki/Wikipedia:Stub", "Template:Algorithm-stub": "/wiki/Template:Algorithm-stub", "Template talk:Algorithm-stub": "/wiki/Template_talk:Algorithm-stub"}