{"Bloom (shader effect)": "/wiki/Bloom_(shader_effect)", "Category:Probabilistic data structures": "/wiki/Category:Probabilistic_data_structures", "Randomized algorithm": "/wiki/Randomized_algorithm", "Data structure": "/wiki/Data_structure", "Count\u2013min sketch": "/wiki/Count%E2%80%93min_sketch", "Quotient filter": "/wiki/Quotient_filter", "Skip list": "/wiki/Skip_list", "Random tree (disambiguation)": "/wiki/Random_tree_(disambiguation)", "Random binary tree": "/wiki/Random_binary_tree", "Treap": "/wiki/Treap", "Rapidly-exploring random tree": "/wiki/Rapidly-exploring_random_tree", "HyperLogLog": "/wiki/HyperLogLog", "Template:Probabilistic": "/wiki/Template:Probabilistic", "Template talk:Probabilistic": "/wiki/Template_talk:Probabilistic", "Probabilistic": "/wiki/Probabilistic", "Element (mathematics)": "/wiki/Element_(mathematics)", "Set (computer science)": "/wiki/Set_(computer_science)", "Type I and type II errors": "/wiki/Type_I_and_type_II_errors", "Hash function": "/wiki/Hash_function", "Hyphenation algorithm": "/wiki/Hyphenation_algorithm", "Core memory": "/wiki/Core_memory", "Bit": "/wiki/Bit", "Edit section: Algorithm description": "/w/index.php?title=Bloom_filter&action=edit&section=1", "Enlarge": "/wiki/File:Bloom_filter.svg", "Bit array": "/wiki/Bit_array", "Map (mathematics)": "/wiki/Map_(mathematics)", "False positive": "/wiki/False_positive", "Double hashing": "/wiki/Double_hashing#Enhanced_double_hashing", "Edit section: Space and time advantages": "/w/index.php?title=Bloom_filter&action=edit&section=2", "Wikipedia:Citation needed": "/wiki/Wikipedia:Citation_needed", "Self-balancing binary search tree": "/wiki/Self-balancing_binary_search_tree", "Trie": "/wiki/Trie", "Hash table": "/wiki/Hash_table", "Array data structure": "/wiki/Array_data_structure", "Linked list": "/wiki/Linked_list", "Information content": "/wiki/Information_content", "Edit section: Probability of false positives": "/w/index.php?title=Bloom_filter&action=edit&section=3", "E (mathematical constant)": "/wiki/E_(mathematical_constant)", "Algorithm": "/wiki/Algorithm", "Stirling numbers of the second kind": "/wiki/Stirling_numbers_of_the_second_kind", "Azuma\u2013Hoeffding inequality": "/wiki/Azuma%E2%80%93Hoeffding_inequality", "Edit section: Optimal number of hash functions": "/w/index.php?title=Bloom_filter&action=edit&section=4", "Edit section: Approximating the number of items in a Bloom filter": "/w/index.php?title=Bloom_filter&action=edit&section=5", "Edit section: The union and intersection of sets": "/w/index.php?title=Bloom_filter&action=edit&section=6", "Edit section: Interesting properties": "/w/index.php?title=Bloom_filter&action=edit&section=7", "Collision resolution scheme": "/wiki/Collision_resolution_scheme", "Union (set theory)": "/wiki/Union_(set_theory)", "Intersection (set theory)": "/wiki/Intersection_(set_theory)", "Bitwise operation": "/wiki/Bitwise_operation", "Superimposed code": "/wiki/Superimposed_code", "Edge-notched card": "/wiki/Edge-notched_card", "Zatocoding": "/wiki/Zatocoding", "Calvin Mooers": "/wiki/Calvin_Mooers", "Edit section: Examples": "/w/index.php?title=Bloom_filter&action=edit&section=8", "Drosophila melanogaster": "/wiki/Drosophila_melanogaster", "Akamai Technologies": "/wiki/Akamai_Technologies", "Content delivery": "/wiki/Content_delivery", "Bigtable": "/wiki/Bigtable", "Apache HBase": "/wiki/Apache_HBase", "Apache Cassandra": "/wiki/Apache_Cassandra", "PostgreSQL": "/wiki/PostgreSQL", "Google Chrome": "/wiki/Google_Chrome", "Bing (search engine)": "/wiki/Bing_(search_engine)", "BitFunnel": "/wiki/BitFunnel", "Inverted files": "/wiki/Inverted_files", "Squid (software)": "/wiki/Squid_(software)", "World Wide Web": "/wiki/World_Wide_Web", "Web cache": "/wiki/Web_cache", "Bitcoin": "/wiki/Bitcoin", "Venti": "/wiki/Venti", "SPIN model checker": "/wiki/SPIN_model_checker", "Cascading (software)": "/wiki/Cascading_(software)", "Exim": "/wiki/Exim", "Medium (publishing platform)": "/wiki/Medium_(publishing_platform)", "Ethereum": "/wiki/Ethereum", "Grafana": "/wiki/Grafana", "Edit section: Alternatives": "/w/index.php?title=Bloom_filter&action=edit&section=9", "Locality of reference": "/wiki/Locality_of_reference", "Cuckoo filter": "/wiki/Cuckoo_filter", "Hash compaction (page does not exist)": "/w/index.php?title=Hash_compaction&action=edit&redlink=1", "Cache misses": "/wiki/Cache_misses", "Golomb coding": "/wiki/Golomb_coding", "Cuckoo hashing": "/wiki/Cuckoo_hashing", "Perfect hash": "/wiki/Perfect_hash", "Edit section: Extensions and applications": "/w/index.php?title=Bloom_filter&action=edit&section=10", "Random projections": "/wiki/Random_projections", "Compressive sensing": "/wiki/Compressive_sensing", "Locality sensitive hashing": "/wiki/Locality_sensitive_hashing", "Edit section: Cache filtering": "/w/index.php?title=Bloom_filter&action=edit&section=11", "Content delivery network": "/wiki/Content_delivery_network", "Edit section: Avoiding false positives in a finite universe": "/w/index.php?title=Bloom_filter&action=edit&section=12", "CRLite": "/wiki/CRLite", "Certificate revocation status": "/wiki/Certificate_revocation_status", "Web PKI (page does not exist)": "/w/index.php?title=Web_PKI&action=edit&redlink=1", "Certificate Transparency": "/wiki/Certificate_Transparency", "Edit section: Counting Bloom filters": "/w/index.php?title=Bloom_filter&action=edit&section=13", "Counting Bloom filter": "/wiki/Counting_Bloom_filter", "Arithmetic overflow": "/wiki/Arithmetic_overflow", "Edit section: Decentralized aggregation": "/w/index.php?title=Bloom_filter&action=edit&section=14", "Data structures": "/wiki/Data_structures", "Aggregate function": "/wiki/Aggregate_function", "Edit section: Distributed Bloom filters": "/w/index.php?title=Bloom_filter&action=edit&section=15", "Processing element": "/wiki/Processing_element", "Shared-nothing architecture": "/wiki/Shared-nothing_architecture", "Bucket sort": "/wiki/Bucket_sort", "Hypercube": "/wiki/Hypercube", "Edit section: Data synchronization": "/w/index.php?title=Bloom_filter&action=edit&section=16", "Data synchronization": "/wiki/Data_synchronization", "Edit section: Bloom filters for streaming data": "/w/index.php?title=Bloom_filter&action=edit&section=17", "Edit section: Bloomier filters": "/w/index.php?title=Bloom_filter&action=edit&section=18", "Associative array": "/wiki/Associative_array", "Edit section: Compact approximators": "/w/index.php?title=Bloom_filter&action=edit&section=19", "Lattice (order)": "/wiki/Lattice_(order)", "Edit section: Parallel Partitioned Bloom Filters": "/w/index.php?title=Bloom_filter&action=edit&section=20", "Edit section: Scalable Bloom filters": "/w/index.php?title=Bloom_filter&action=edit&section=21", "Edit section: Spatial Bloom filters": "/w/index.php?title=Bloom_filter&action=edit&section=22", "Location information": "/wiki/Location_information", "Information privacy": "/wiki/Information_privacy", "Edit section: Layered Bloom filters": "/w/index.php?title=Bloom_filter&action=edit&section=23", "Edit section: Attenuated Bloom filters": "/w/index.php?title=Bloom_filter&action=edit&section=24", "Edit section: Chemical structure searching": "/w/index.php?title=Bloom_filter&action=edit&section=25", "Chemical similarity": "/wiki/Chemical_similarity", "Pseudorandom number generator": "/wiki/Pseudorandom_number_generator", "Edit section: See also": "/w/index.php?title=Bloom_filter&action=edit&section=26", "Portal:Computer programming": "/wiki/Portal:Computer_programming", "Feature hashing": "/wiki/Feature_hashing", "MinHash": "/wiki/MinHash", "Bloom filters in bioinformatics": "/wiki/Bloom_filters_in_bioinformatics", "Edit section: Notes": "/w/index.php?title=Bloom_filter&action=edit&section=27", "Doi (identifier)": "/wiki/Doi_(identifier)", "ISBN (identifier)": "/wiki/ISBN_(identifier)", "Special:BookSources/978-3-030-53290-1": "/wiki/Special:BookSources/978-3-030-53290-1", "PMC (identifier)": "/wiki/PMC_(identifier)", "Bibcode (identifier)": "/wiki/Bibcode_(identifier)", "ISSN (identifier)": "/wiki/ISSN_(identifier)", "PMID (identifier)": "/wiki/PMID_(identifier)", "S2CID (identifier)": "/wiki/S2CID_(identifier)", "GitHub": "/wiki/GitHub", "ArXiv (identifier)": "/wiki/ArXiv_(identifier)", "Special:BookSources/978-1-5090-5533-3": "/wiki/Special:BookSources/978-1-5090-5533-3", "Special:BookSources/978-1-4799-1293-3": "/wiki/Special:BookSources/978-1-4799-1293-3", "Special:BookSources/978-3-030-58149-7": "/wiki/Special:BookSources/978-3-030-58149-7", "Edit section: References": "/w/index.php?title=Bloom_filter&action=edit&section=28", "CiteSeerX (identifier)": "/wiki/CiteSeerX_(identifier)", "Special:BookSources/978-1-4244-0035-5": "/wiki/Special:BookSources/978-1-4244-0035-5", "Special:BookSources/978-1-4244-1229-7": "/wiki/Special:BookSources/978-1-4244-1229-7", "Hdl (identifier)": "/wiki/Hdl_(identifier)", "Communications of the ACM": "/wiki/Communications_of_the_ACM", "Michael Mitzenmacher": "/wiki/Michael_Mitzenmacher", "George Varghese": "/wiki/George_Varghese", "Lecture Notes in Computer Science": "/wiki/Lecture_Notes_in_Computer_Science", "Special:BookSources/978-3-540-38875-3": "/wiki/Special:BookSources/978-3-540-38875-3", "Andrei Broder": "/wiki/Andrei_Broder", "IEEE/ACM Transactions on Networking": "/wiki/IEEE/ACM_Transactions_on_Networking", "Special:BookSources/978-3-540-87743-1": "/wiki/Special:BookSources/978-3-540-87743-1", "Bernard Chazelle": "/wiki/Bernard_Chazelle", "Ronitt Rubinfeld": "/wiki/Ronitt_Rubinfeld", "Ayellet Tal": "/wiki/Ayellet_Tal", "Special:BookSources/978-1581136340": "/wiki/Special:BookSources/978-1581136340", "Special:BookSources/978-1595935809": "/wiki/Special:BookSources/978-1595935809", "Rasmus Pagh": "/wiki/Rasmus_Pagh", "Special:BookSources/978-3-540-70574-1": "/wiki/Special:BookSources/978-3-540-70574-1", "David Eppstein": "/wiki/David_Eppstein", "Michael T. Goodrich": "/wiki/Michael_T._Goodrich", "Workshop on Algorithms and Data Structures": "/wiki/Workshop_on_Algorithms_and_Data_Structures", "Special:BookSources/9781450332798": "/wiki/Special:BookSources/9781450332798", "Jussara M. Almeida": "/wiki/Jussara_M._Almeida", "Bruce Maggs": "/wiki/Bruce_Maggs", "Ramesh Sitaraman": "/wiki/Ramesh_Sitaraman", "Eli Upfal": "/wiki/Eli_Upfal", "Special:BookSources/9780521835404": "/wiki/Special:BookSources/9780521835404", "Mihai P\u0103tra\u0219cu (computer scientist)": "/wiki/Mihai_P%C4%83tra%C8%99cu_(computer_scientist)", "Special:BookSources/978-1581139600": "/wiki/Special:BookSources/978-1581139600", "Special:BookSources/978-3-319-16744-2": "/wiki/Special:BookSources/978-3-319-16744-2", "Special:BookSources/978-3-642-03350-6": "/wiki/Special:BookSources/978-3-642-03350-6", "Frances Brazier": "/wiki/Frances_Brazier", "Peter Sanders (computer scientist)": "/wiki/Peter_Sanders_(computer_scientist)", "Special:BookSources/978-3-540-72844-3": "/wiki/Special:BookSources/978-3-540-72844-3", "Special:BookSources/978-1-4673-0773-4": "/wiki/Special:BookSources/978-1-4673-0773-4", "Special:BookSources/978-0-7695-2043-8": "/wiki/Special:BookSources/978-0-7695-2043-8", "Pierre Baldi": "/wiki/Pierre_Baldi", "Special:BookSources/978-0-596-00162-9": "/wiki/Special:BookSources/978-0-596-00162-9", "Special:BookSources/978-1-4244-6539-2": "/wiki/Special:BookSources/978-1-4244-6539-2", "Edit section: External links": "/w/index.php?title=Bloom_filter&action=edit&section=29", "commons:Category:Bloom filter": "https://commons.wikimedia.org/wiki/Category:Bloom_filter", "Perl": "/wiki/Perl", "University of Wisconsin\u2013Madison": "/wiki/University_of_Wisconsin%E2%80%93Madison", "YouTube": "/wiki/YouTube"}