{"Outline (list)": "/wiki/Outline_(list)", "Regression analysis": "/wiki/Regression_analysis", "Statistics": "/wiki/Statistics", "Dependent variable": "/wiki/Dependent_variable", "Independent variable": "/wiki/Independent_variable", "Edit section: Overview articles": "/w/index.php?title=Outline_of_regression_analysis&action=edit&section=1", "Linear regression": "/wiki/Linear_regression", "Edit section: Non-statistical articles related to regression": "/w/index.php?title=Outline_of_regression_analysis&action=edit&section=2", "Least squares": "/wiki/Least_squares", "Linear least squares (mathematics)": "/wiki/Linear_least_squares_(mathematics)", "Non-linear least squares": "/wiki/Non-linear_least_squares", "Least absolute deviations": "/wiki/Least_absolute_deviations", "Curve fitting": "/wiki/Curve_fitting", "Smoothing": "/wiki/Smoothing", "Cross-sectional study": "/wiki/Cross-sectional_study", "Edit section: Basic statistical ideas related to regression": "/w/index.php?title=Outline_of_regression_analysis&action=edit&section=3", "Conditional expectation": "/wiki/Conditional_expectation", "Correlation": "/wiki/Correlation", "Pearson product-moment correlation coefficient": "/wiki/Pearson_product-moment_correlation_coefficient", "Mean square error": "/wiki/Mean_square_error", "Residual sum of squares": "/wiki/Residual_sum_of_squares", "Explained sum of squares": "/wiki/Explained_sum_of_squares", "Total sum of squares": "/wiki/Total_sum_of_squares", "Edit section: Visualization": "/w/index.php?title=Outline_of_regression_analysis&action=edit&section=4", "Scatterplot": "/wiki/Scatterplot", "Edit section: Linear regression based on least squares": "/w/index.php?title=Outline_of_regression_analysis&action=edit&section=5", "General linear model": "/wiki/General_linear_model", "Ordinary least squares": "/wiki/Ordinary_least_squares", "Generalized least squares": "/wiki/Generalized_least_squares", "Simple linear regression": "/wiki/Simple_linear_regression", "Trend estimation": "/wiki/Trend_estimation", "Ridge regression": "/wiki/Ridge_regression", "Polynomial regression": "/wiki/Polynomial_regression", "Segmented regression": "/wiki/Segmented_regression", "Nonlinear regression": "/wiki/Nonlinear_regression", "Edit section: Generalized linear models": "/w/index.php?title=Outline_of_regression_analysis&action=edit&section=6", "Generalized linear models": "/wiki/Generalized_linear_models", "Logistic regression": "/wiki/Logistic_regression", "Multinomial logit": "/wiki/Multinomial_logit", "Ordered logit": "/wiki/Ordered_logit", "Probit model": "/wiki/Probit_model", "Multinomial probit": "/wiki/Multinomial_probit", "Ordered probit": "/wiki/Ordered_probit", "Poisson regression": "/wiki/Poisson_regression", "Maximum likelihood": "/wiki/Maximum_likelihood", "Cochrane\u2013Orcutt estimation": "/wiki/Cochrane%E2%80%93Orcutt_estimation", "Edit section: Computation": "/w/index.php?title=Outline_of_regression_analysis&action=edit&section=7", "Numerical methods for linear least squares": "/wiki/Numerical_methods_for_linear_least_squares", "Edit section: Inference for regression models": "/w/index.php?title=Outline_of_regression_analysis&action=edit&section=8", "F-test": "/wiki/F-test", "T-test": "/wiki/T-test", "Lack-of-fit sum of squares": "/wiki/Lack-of-fit_sum_of_squares", "Confidence band": "/wiki/Confidence_band", "Coefficient of determination": "/wiki/Coefficient_of_determination", "Multiple correlation": "/wiki/Multiple_correlation", "Scheff\u00e9's method": "/wiki/Scheff%C3%A9%27s_method", "Edit section: Challenges to regression modeling": "/w/index.php?title=Outline_of_regression_analysis&action=edit&section=9", "Autocorrelation": "/wiki/Autocorrelation", "Cointegration": "/wiki/Cointegration", "Multicollinearity": "/wiki/Multicollinearity", "Homoscedastic": "/wiki/Homoscedastic", "Goodness of fit": "/wiki/Goodness_of_fit", "Normality test": "/wiki/Normality_test", "Outlier": "/wiki/Outlier", "Edit section: Diagnostics for regression models": "/w/index.php?title=Outline_of_regression_analysis&action=edit&section=10", "Regression model validation": "/wiki/Regression_model_validation", "Studentized residual": "/wiki/Studentized_residual", "Cook's distance": "/wiki/Cook%27s_distance", "Variance inflation factor": "/wiki/Variance_inflation_factor", "DFFITS": "/wiki/DFFITS", "Partial residual plot": "/wiki/Partial_residual_plot", "Partial regression plot": "/wiki/Partial_regression_plot", "Leverage (statistics)": "/wiki/Leverage_(statistics)", "Durbin\u2013Watson statistic": "/wiki/Durbin%E2%80%93Watson_statistic", "Condition number": "/wiki/Condition_number", "Edit section: Formal aids to model selection": "/w/index.php?title=Outline_of_regression_analysis&action=edit&section=11", "Model selection": "/wiki/Model_selection", "Mallows's Cp": "/wiki/Mallows%27s_Cp", "Akaike information criterion": "/wiki/Akaike_information_criterion", "Bayesian information criterion": "/wiki/Bayesian_information_criterion", "Hannan\u2013Quinn information criterion": "/wiki/Hannan%E2%80%93Quinn_information_criterion", "Cross-validation (statistics)": "/wiki/Cross-validation_(statistics)", "Edit section: Robust regression": "/w/index.php?title=Outline_of_regression_analysis&action=edit&section=12", "Robust regression": "/wiki/Robust_regression", "Edit section: Terminology": "/w/index.php?title=Outline_of_regression_analysis&action=edit&section=13", "Linear model": "/wiki/Linear_model", "Dependent and independent variables": "/wiki/Dependent_and_independent_variables", "Errors and residuals in statistics": "/wiki/Errors_and_residuals_in_statistics", "Hat matrix": "/wiki/Hat_matrix", "Trend-stationary process": "/wiki/Trend-stationary_process", "Cross-sectional data": "/wiki/Cross-sectional_data", "Time series": "/wiki/Time_series", "Edit section: Methods for dependent data": "/w/index.php?title=Outline_of_regression_analysis&action=edit&section=14", "Mixed model": "/wiki/Mixed_model", "Random effects model": "/wiki/Random_effects_model", "Hierarchical linear models": "/wiki/Hierarchical_linear_models", "Edit section: Nonparametric regression": "/w/index.php?title=Outline_of_regression_analysis&action=edit&section=15", "Nonparametric regression": "/wiki/Nonparametric_regression", "Isotonic regression": "/wiki/Isotonic_regression", "Edit section: Semiparametric regression": "/w/index.php?title=Outline_of_regression_analysis&action=edit&section=16", "Semiparametric regression": "/wiki/Semiparametric_regression", "Local regression": "/wiki/Local_regression", "Edit section: Other forms of regression": "/w/index.php?title=Outline_of_regression_analysis&action=edit&section=17", "Total least squares": "/wiki/Total_least_squares", "Deming regression": "/wiki/Deming_regression", "Errors-in-variables model": "/wiki/Errors-in-variables_model", "Instrumental variables": "/wiki/Instrumental_variables", "Quantile regression": "/wiki/Quantile_regression", "Generalized additive model": "/wiki/Generalized_additive_model", "Autoregressive model": "/wiki/Autoregressive_model", "Moving average model": "/wiki/Moving_average_model", "Autoregressive moving average model": "/wiki/Autoregressive_moving_average_model", "Autoregressive integrated moving average": "/wiki/Autoregressive_integrated_moving_average", "Autoregressive conditional heteroskedasticity": "/wiki/Autoregressive_conditional_heteroskedasticity", "Edit section: See also": "/w/index.php?title=Outline_of_regression_analysis&action=edit&section=18", "Wikipedia:Wikimedia sister projects": "/wiki/Wikipedia:Wikimedia_sister_projects", "wikt:Special:Search/Regression analysis": "https://en.wiktionary.org/wiki/Special:Search/Regression_analysis", "c:Category:Regression analysis": "https://commons.wikimedia.org/wiki/Category:Regression_analysis", "n:Special:Search/Regression analysis": "https://en.wikinews.org/wiki/Special:Search/Regression_analysis", "q:Special:Search/Regression analysis": "https://en.wikiquote.org/wiki/Special:Search/Regression_analysis", "s:Special:Search/Regression analysis": "https://en.wikisource.org/wiki/Special:Search/Regression_analysis", "b:Special:Search/Regression analysis": "https://en.wikibooks.org/wiki/Special:Search/Regression_analysis", "v:Special:Search/Regression analysis": "https://en.wikiversity.org/wiki/Special:Search/Regression_analysis", "Prediction": "/wiki/Prediction", "Design of experiments": "/wiki/Design_of_experiments", "Data transformation (statistics)": "/wiki/Data_transformation_(statistics)", "Power transform": "/wiki/Power_transform", "Machine learning": "/wiki/Machine_learning", "ANOVA": "/wiki/ANOVA", "Causality": "/wiki/Causality", "Template:Outline footer": "/wiki/Template:Outline_footer", "Template talk:Outline footer": "/wiki/Template_talk:Outline_footer", "Wikipedia:Contents/Outlines": "/wiki/Wikipedia:Contents/Outlines"}