{"Regulation": "/wiki/Regulation", "Algorithm": "/wiki/Algorithm", "Artificial intelligence": "/wiki/Artificial_intelligence", "Machine learning": "/wiki/Machine_learning", "Right": "/wiki/Right", "Explanation": "/wiki/Explanation", "Individual right": "/wiki/Individual_right", "Credit bureau": "/wiki/Credit_bureau", "Legal right": "/wiki/Legal_right", "Automated decision-making": "/wiki/Automated_decision-making", "Trustworthy": "/wiki/Trustworthy", "Professional": "/wiki/Professional", "Edit section: Examples": "/w/index.php?title=Right_to_explanation&action=edit&section=1", "Edit section: Credit scoring in the United States": "/w/index.php?title=Right_to_explanation&action=edit&section=2", "Credit score in the United States": "/wiki/Credit_score_in_the_United_States", "Equal Credit Opportunity Act": "/wiki/Equal_Credit_Opportunity_Act", "Code of Federal Regulations": "/wiki/Code_of_Federal_Regulations", "Edit section: European Union": "/w/index.php?title=Right_to_explanation&action=edit&section=3", "General Data Protection Regulation": "/wiki/General_Data_Protection_Regulation", "Data Protection Directive": "/wiki/Data_Protection_Directive", "Automated decision": "/wiki/Automated_decision", "Edit section: France": "/w/index.php?title=Right_to_explanation&action=edit&section=4", "France": "/wiki/France", "Edit section: South Korea": "/w/index.php?title=Right_to_explanation&action=edit&section=5", "Edit section: China": "/w/index.php?title=Right_to_explanation&action=edit&section=6", "Edit section: Criticism": "/w/index.php?title=Right_to_explanation&action=edit&section=7", "Algorithmic accountability": "/wiki/Algorithmic_accountability", "Deep neural network": "/wiki/Deep_neural_network", "Explainable AI": "/wiki/Explainable_AI", "Gut feeling": "/wiki/Gut_feeling", "Edit section: Suggestions": "/w/index.php?title=Right_to_explanation&action=edit&section=8", "Edit section: See also": "/w/index.php?title=Right_to_explanation&action=edit&section=9", "Algorithmic transparency": "/wiki/Algorithmic_transparency", "Explainable artificial intelligence": "/wiki/Explainable_artificial_intelligence", "Regulation of algorithms": "/wiki/Regulation_of_algorithms", "Edit section: References": "/w/index.php?title=Right_to_explanation&action=edit&section=10", "ISBN (identifier)": "/wiki/ISBN_(identifier)", "Special:BookSources/9781785421051": "/wiki/Special:BookSources/9781785421051", "Consumer Financial Protection Bureau": "/wiki/Consumer_Financial_Protection_Bureau", "ArXiv (identifier)": "/wiki/ArXiv_(identifier)", "Doi (identifier)": "/wiki/Doi_(identifier)", "S2CID (identifier)": "/wiki/S2CID_(identifier)", "SSRN (identifier)": "/wiki/SSRN_(identifier)", "ISSN (identifier)": "/wiki/ISSN_(identifier)", "Special:BookSources/978-1-4503-6125-5": "/wiki/Special:BookSources/978-1-4503-6125-5", "Special:BookSources/978-1-4503-6936-7": "/wiki/Special:BookSources/978-1-4503-6936-7"}