{"Enlarge": "/wiki/File:Scan-line_algorithm.svg", "Hidden-surface determination": "/wiki/Hidden-surface_determination#Visible_surface_determination", "3D computer graphics": "/wiki/3D_computer_graphics", "Polygon": "/wiki/Polygon", "Pixel": "/wiki/Pixel", "Scan line": "/wiki/Scan_line", "Vertex (geometry)": "/wiki/Vertex_(geometry)", "Cache memory": "/wiki/Cache_memory", "Phong reflection model": "/wiki/Phong_reflection_model", "Z-buffer": "/wiki/Z-buffer", "Edit section: Algorithm": "/w/index.php?title=Scanline_rendering&action=edit&section=1", "Bubble sort": "/wiki/Bubble_sort", "Wikipedia:Citation needed": "/wiki/Wikipedia:Citation_needed", "Edit section: Variants": "/w/index.php?title=Scanline_rendering&action=edit&section=2", "Z-buffering": "/wiki/Z-buffering", "Deferred shading": "/wiki/Deferred_shading", "Edit section: History": "/w/index.php?title=Scanline_rendering&action=edit&section=3", "Ivan Sutherland": "/wiki/Ivan_Sutherland", "University of Utah": "/wiki/University_of_Utah", "Evans & Sutherland": "/wiki/Evans_%26_Sutherland", "Salt Lake City": "/wiki/Salt_Lake_City", "Edit section: Use in realtime rendering": "/w/index.php?title=Scanline_rendering&action=edit&section=4", "Framebuffer": "/wiki/Framebuffer", "Nintendo DS": "/wiki/Nintendo_DS", "Sprite (computer graphics)": "/wiki/Sprite_(computer_graphics)", "Binary space partitioning": "/wiki/Binary_space_partitioning", "Painter's algorithm": "/wiki/Painter%27s_algorithm", "Texture mapping": "/wiki/Texture_mapping", "Cell (microprocessor)": "/wiki/Cell_(microprocessor)", "PlayStation 3": "/wiki/PlayStation_3", "Edit section: Similar techniques": "/w/index.php?title=Scanline_rendering&action=edit&section=5", "Tiled rendering": "/wiki/Tiled_rendering", "PowerVR": "/wiki/PowerVR", "Dreamcast": "/wiki/Dreamcast", "Edit section: Comparison with Z-buffer algorithm": "/w/index.php?title=Scanline_rendering&action=edit&section=6", "Edit section: See also": "/w/index.php?title=Scanline_rendering&action=edit&section=7", "Raster scan": "/wiki/Raster_scan", "Ray tracing (graphics)": "/wiki/Ray_tracing_(graphics)", "Edit section: References": "/w/index.php?title=Scanline_rendering&action=edit&section=8", "Edit section: External links": "/w/index.php?title=Scanline_rendering&action=edit&section=9", "Template:Computer graphics": "/wiki/Template:Computer_graphics", "Template talk:Computer graphics": "/wiki/Template_talk:Computer_graphics", "Computer graphics (computer science)": "/wiki/Computer_graphics_(computer_science)", "Vector graphics": "/wiki/Vector_graphics", "Diffusion curve": "/wiki/Diffusion_curve", "2D computer graphics": "/wiki/2D_computer_graphics", "2.5D": "/wiki/2.5D", "Isometric video game graphics": "/wiki/Isometric_video_game_graphics", "Mode 7": "/wiki/Mode_7", "Parallax scrolling": "/wiki/Parallax_scrolling", "Ray casting": "/wiki/Ray_casting", "Skybox (video games)": "/wiki/Skybox_(video_games)", "Alpha compositing": "/wiki/Alpha_compositing", "Layers (digital image editing)": "/wiki/Layers_(digital_image_editing)", "Text-to-image": "/wiki/Text-to-image", "3D projection": "/wiki/3D_projection", "3D rendering": "/wiki/3D_rendering", "Image-based modeling and rendering": "/wiki/Image-based_modeling_and_rendering", "Spectral rendering": "/wiki/Spectral_rendering", "Unbiased rendering": "/wiki/Unbiased_rendering", "Aliasing": "/wiki/Aliasing", "Anisotropic filtering": "/wiki/Anisotropic_filtering", "Cel shading": "/wiki/Cel_shading", "Computer graphics lighting": "/wiki/Computer_graphics_lighting", "Global illumination": "/wiki/Global_illumination", "Polygon mesh": "/wiki/Polygon_mesh", "Triangle mesh": "/wiki/Triangle_mesh", "Shading": "/wiki/Shading", "Surface triangulation": "/wiki/Surface_triangulation", "Wire-frame model": "/wiki/Wire-frame_model", "Affine transformation": "/wiki/Affine_transformation", "Back-face culling": "/wiki/Back-face_culling", "Clipping (computer graphics)": "/wiki/Clipping_(computer_graphics)", "Collision detection": "/wiki/Collision_detection", "Planar projection": "/wiki/Planar_projection", "Rendering (computer graphics)": "/wiki/Rendering_(computer_graphics)", "Rotation (mathematics)": "/wiki/Rotation_(mathematics)", "Scaling (geometry)": "/wiki/Scaling_(geometry)", "Shadow mapping": "/wiki/Shadow_mapping", "Shadow volume": "/wiki/Shadow_volume", "Shear matrix": "/wiki/Shear_matrix", "Translation (geometry)": "/wiki/Translation_(geometry)", "List of computer graphics algorithms": "/wiki/List_of_computer_graphics_algorithms"}