{"Enlarge": "/wiki/File:StrandSort.gif", "Recursion (computer science)": "/wiki/Recursion_(computer_science)", "Sorting algorithm": "/wiki/Sorting_algorithm", "Big O notation": "/wiki/Big_O_notation", "Time complexity": "/wiki/Time_complexity", "Wikipedia:Citation needed": "/wiki/Wikipedia:Citation_needed", "J Sort (page does not exist)": "/w/index.php?title=J_Sort&action=edit&redlink=1", "Edit section: Example": "/w/index.php?title=Strand_sort&action=edit&section=1", "Edit section: Implementation": "/w/index.php?title=Strand_sort&action=edit&section=2", "Edit section: References": "/w/index.php?title=Strand_sort&action=edit&section=3", "ISBN (identifier)": "/wiki/ISBN_(identifier)", "Special:BookSources/9788174466761": "/wiki/Special:BookSources/9788174466761", "OCLC (identifier)": "/wiki/OCLC_(identifier)", "Template:Cite book": "/wiki/Template:Cite_book", "Category:CS1 maint: others": "/wiki/Category:CS1_maint:_others", "Special:BookSources/9780070667655": "/wiki/Special:BookSources/9780070667655"}